README.rst
setup.py
ubidots/__init__.py
ubidots/apiclient.py
ubidots.egg-info/PKG-INFO
ubidots.egg-info/SOURCES.txt
ubidots.egg-info/dependency_links.txt
ubidots.egg-info/pbr.json
ubidots.egg-info/requires.txt
ubidots.egg-info/top_level.txt