Metadata-Version: 1.1
Name: ubidots
Version: 1.6.5
Summary: Api Client to connect to ubidots.com api version 1.6
Home-page: https://github.com/ubidots/ubidots-python/
Author: Ubidots Team
Author-email: devel@ubidots.com
License: MIT
Platform: any
Classifier: Development Status :: 5 - Production/Stable
Classifier: Intended Audience :: Developers
Classifier: License :: OSI Approved :: MIT License
Classifier: Operating System :: OS Independent
Classifier: Programming Language :: Python
Classifier: Programming Language :: Python :: 2.5
Classifier: Programming Language :: Python :: 2.6
Classifier: Programming Language :: Python :: 2.7
Classifier: Programming Language :: Python :: 3.4
Classifier: Topic :: Software Development :: Libraries :: Python Modules
Classifier: Topic :: System :: Hardware
